example_project/__init__.py
example_project/main.py
example_project/jobs/__init__.py
example_project/jobs/get_ip.py
example_project/jobs/notify_boot.py
example_project/jobs/ping_cron.py
git_syncer/__init__.py
git_syncer/executor.py
git_syncer/main.py
git_syncer/models.py
git_syncer/run_boot.py
git_syncer/run_crons.py
git_syncer/runnables.py
git_syncer/initializer/__init__.py
git_syncer/initializer/initialize.py
git_syncer/initializer/__pycache__/__init__.cpython-38.pyc
git_syncer/initializer/__pycache__/initialize.cpython-38.pyc
git_syncer/initializer/templates/crontab.txt
git_syncer/initializer/templates/runner.txt
git_syncer/utils/__init__.py
git_syncer/utils/logger.py
git_syncer/utils/shell.py
git_syncer-1.1.1.dist-info/LICENSE
git_syncer-1.1.1.dist-info/METADATA
git_syncer-1.1.1.dist-info/WHEEL
git_syncer-1.1.1.dist-info/entry_points.txt
git_syncer-1.1.1.dist-info/top_level.txt
git_syncer-1.1.1.dist-info/RECORD
