Metadata-Version: 2.1
Name: git-syncer
Version: 1.1.1
Summary: Allows cron job control and command execution on a remote machine using git infrastructure
Home-page: https://github.com/asaf-kali/git-syncer
Author: Asaf Kali
Author-email: asaf.kali@mail.huji.ac.il
License: https://github.com/asaf-kali/git-syncer/blob/main/LICENSE
Classifier: Programming Language :: Python :: 3
Classifier: License :: OSI Approved :: MIT License
Classifier: Operating System :: OS Independent
Requires-Python: >=3.6
License-File: LICENSE
Requires-Dist: pycron >=3.0.0
Requires-Dist: jinja2 >=3.0.0
